birkhoff.py
birkhoff-0.0.5.dist-info/DESCRIPTION.rst
birkhoff-0.0.5.dist-info/METADATA
birkhoff-0.0.5.dist-info/RECORD
birkhoff-0.0.5.dist-info/WHEEL
birkhoff-0.0.5.dist-info/metadata.json
birkhoff-0.0.5.dist-info/top_level.txt
