Metadata-Version: 2.0
Name: birkhoff
Version: 0.0.5
Summary: Birkhoff--von Neumann decomposition for doubly stochastic matrices
Home-page: https://github.com/jfinkels/birkhoff
Author: Jeffrey Finkelstein
Author-email: jeffrey.finkelstein@gmail.com
License: GNU GPLv3+
Download-URL: https://github.com/jfinkels/birkhoff
Platform: any
Requires-Dist: numpy
Requires-Dist: networkx (>=2.0)
